{
	"programs": [{
		"program_id": "1",
		"facility_id": "1",
		"facility_name": "Facility Name",
		"program_name": "Program Name",
		"type": "Type of Program",
		"address": "12345 Street Address",
		"city": "City",
		"state": "ST",
		"postal_code": "55555",
		"phone": "555-555-5555",
		"contact_name": "John Doe",
		"contact_phone": "555-555-5555"
	},
	{
		"program_id": "2",
		"facility_id": "2",
		"facility_name": "Facility Name",
		"program_name": "Program Name",
		"type": "Type of Program",
		"address": "12345 Street Address",
		"city": "City",
		"state": "ST",
		"postal_code": "55555",
		"phone": "555-555-5555",
		"contact_name": "John Doe",
		"contact_phone": "555-555-5555"
	},
	{
		"program_id": "3",
		"facility_id": "3",
		"facility_name": "Facility Name",
		"program_name": "Program Name",
		"type": "Type of Program",
		"address": "12345 Street Address",
		"city": "City",
		"state": "ST",
		"postal_code": "55555",
		"phone": "555-555-5555",
		"contact_name": "John Doe",
		"contact_phone": "555-555-5555"
	},
	{
		"program_id": "4",
		"facility_id": "4",
		"facility_name": "Facility Name",
		"program_name": "Program Name",
		"type": "Type of Program",
		"address": "12345 Street Address",
		"city": "City",
		"state": "ST",
		"postal_code": "55555",
		"phone": "555-555-5555",
		"contact_name": "John Doe",
		"contact_phone": "555-555-5555"
	},
	{
		"program_id": "5",
		"facility_id": "5",
		"facility_name": "Facility Name",
		"program_name": "Program Name",
		"type": "Type of Program",
		"address": "12345 Street Address",
		"city": "City",
		"state": "ST",
		"postal_code": "55555",
		"phone": "555-555-5555",
		"contact_name": "John Doe",
		"contact_phone": "555-555-5555"
	}
	]
}